{
    "client": {
        "id":"3054702082-27vrnp0vmeu5mm03hv2ll9im7b39u7m5.apps.googleusercontent.com",
        "secret":"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",
        "redirect":"https://cloudappwp.azurewebsites.net/auth/google/callback"
    },
    "credentials": {
        "access_token": "token",
        "token_type": "bearer",
        "expires_in": 3600,
        "refresh_token": "refresh_token"
    },
    "web": {
        "project_id":"cloudappwp",
        "auth_uri":"https://accounts.google.com/o/oauth2/auth",
        "token_uri":"https://oauth2.googleapis.com/token",
        "auth_provider_x509_cert_url":"https://www.googleapis.com/oauth2/v1/certs",
        "javascript_origins":["https://cloudappwp.azurewebsites.net"]
    }
}